[
  {
    "id": "tr001",
    "name": "Rajdhani Express",
    "departure": "Delhi",
    "arrival": "Mumbai",
    "departureTime": "16:55",
    "arrivalTime": "08:35",
    "duration": "15h 40m",
    "price": 1850,
    "availableSeats": 45,
    "rating": 4.5,
    "class": "3A",
    "amenities": ["WiFi", "Meals", "AC", "Charging Point"]
  },
  {
    "id": "tr002",
    "name": "Duronto Express",
    "departure": "Delhi",
    "arrival": "Mumbai",
    "departureTime": "22:00",
    "arrivalTime": "12:30",
    "duration": "14h 30m",
    "price": 2200,
    "availableSeats": 32,
    "rating": 4.7,
    "class": "2A",
    "amenities": ["WiFi", "Meals", "AC", "Bedroll", "Charging Point"]
  },
  {
    "id": "tr003",
    "name": "Garib Rath",
    "departure": "Delhi",
    "arrival": "Mumbai",
    "departureTime": "13:30",
    "arrivalTime": "06:00",
    "duration": "16h 30m",
    "price": 950,
    "availableSeats": 78,
    "rating": 4.0,
    "class": "Sleeper",
    "amenities": ["AC", "Charging Point"]
  },
  {
    "id": "tr004",
    "name": "Vijayawada Express",
    "departure": "Delhi",
    "arrival": "Hyderabad",
    "departureTime": "06:00",
    "arrivalTime": "20:30",
    "duration": "14h 30m",
    "price": 1650,
    "availableSeats": 52,
    "rating": 4.3,
    "class": "3A",
    "amenities": ["WiFi", "Meals", "AC", "Charging Point"]
  },
  {
    "id": "tr005",
    "name": "Howrah Mail",
    "departure": "Delhi",
    "arrival": "Kolkata",
    "departureTime": "23:45",
    "arrivalTime": "17:30",
    "duration": "17h 45m",
    "price": 1450,
    "availableSeats": 38,
    "rating": 4.2,
    "class": "3A",
    "amenities": ["WiFi", "Meals", "AC", "Charging Point", "Bedroll"]
  },
  {
    "id": "tr006",
    "name": "Chennai Express",
    "departure": "Delhi",
    "arrival": "Chennai",
    "departureTime": "14:15",
    "arrivalTime": "10:00",
    "duration": "19h 45m",
    "price": 2100,
    "availableSeats": 28,
    "rating": 4.4,
    "class": "2A",
    "amenities": ["WiFi", "Meals", "AC", "Bedroll", "Charging Point"]
  },
  {
    "id": "tr007",
    "name": "Karnataka Express",
    "departure": "Delhi",
    "arrival": "Bangalore",
    "departureTime": "19:30",
    "arrivalTime": "12:15",
    "duration": "16h 45m",
    "price": 2350,
    "availableSeats": 22,
    "rating": 4.6,
    "class": "1A",
    "amenities": ["WiFi", "Meals", "AC", "Bedroll", "Charging Point", "WiFi"]
  },
  {
    "id": "tr008",
    "name": "Goa Express",
    "departure": "Delhi",
    "arrival": "Goa",
    "departureTime": "15:00",
    "arrivalTime": "13:30",
    "duration": "22h 30m",
    "price": 1250,
    "availableSeats": 65,
    "rating": 4.1,
    "class": "Sleeper",
    "amenities": ["AC", "Charging Point", "Meals"]
  },
  {
    "id": "tr009",
    "name": "Samjhauta Express",
    "departure": "Delhi",
    "arrival": "Amritsar",
    "departureTime": "21:30",
    "arrivalTime": "05:00",
    "duration": "7h 30m",
    "price": 650,
    "availableSeats": 90,
    "rating": 3.9,
    "class": "Sleeper",
    "amenities": ["Charging Point"]
  },
  {
    "id": "tr010",
    "name": "Vande Bharat",
    "departure": "Delhi",
    "arrival": "Mumbai",
    "departureTime": "06:00",
    "arrivalTime": "15:30",
    "duration": "9h 30m",
    "price": 2850,
    "availableSeats": 18,
    "rating": 4.8,
    "class": "1A",
    "amenities": ["WiFi", "Meals", "AC", "Charging Point", "Entertainment"]
  }
]
